codiga/__init__.py
codiga/__main__.py
codiga/analyze.py
codiga/check_quality.py
codiga/common.py
codiga/compare.py
codiga/constants.py
codiga/git_hook.py
codiga/github_action.py
codiga/project.py
codiga/snippets_imports.py
codiga/version.py
codiga/exceptions/__init__.py
codiga/exceptions/git_command_exception.py
codiga/graphql/__init__.py
codiga/graphql/common.py
codiga/graphql/constants.py
codiga/graphql/file_analysis.py
codiga/graphql/project.py
codiga/graphql/recipe.py
codiga/graphql/rosie.py
codiga/model/__init__.py
codiga/model/rosie_rule.py
codiga/model/violation.py
codiga/rosie/__init__.py
codiga/rosie/api.py
codiga/rosie/ruleset.py
codiga/snippets/__init__.py
codiga/snippets/convert.py
codiga/utils/__init__.py
codiga/utils/file_utils.py
codiga/utils/git.py
codiga/utils/patch_utils.py
codiga/utils/violation_utils.py
codiga-0.1.2.dist-info/LICENSE
codiga-0.1.2.dist-info/METADATA
codiga-0.1.2.dist-info/WHEEL
codiga-0.1.2.dist-info/entry_points.txt
codiga-0.1.2.dist-info/top_level.txt
codiga-0.1.2.dist-info/RECORD
