Metadata-Version: 2.1
Name: codiga
Version: 0.1.2
Summary: CLI tools for codiga.io
Home-page: https://github.com/codiga/clitool
Author: codiga
License: BSD
Project-URL: Changelog, https://github.com/codiga/clitool/blob/master/CHANGELOG.md
Project-URL: Docs, https://github.com/codiga/clitool/
Platform: UNKNOWN
Classifier: Development Status :: 5 - Production/Stable
Classifier: Topic :: Software Development :: Testing
Classifier: Intended Audience :: Developers
Classifier: License :: OSI Approved :: BSD License
Classifier: Operating System :: OS Independent
Classifier: Programming Language :: Python
Classifier: Programming Language :: Python :: 3.5
Classifier: Programming Language :: Python :: 3.6
Classifier: Programming Language :: Python :: 3.7
Classifier: Programming Language :: Python :: Implementation :: CPython
Classifier: Programming Language :: Python :: Implementation :: PyPy
License-File: LICENSE
Requires-Dist: docopt (>=0.6.2)
Requires-Dist: requests (>=2.27.1)
Requires-Dist: unidiff (>=0.7.4)
Requires-Dist: tenacity (>=8.1.0)
Requires-Dist: pyyaml (>=6.0)
Requires-Dist: urllib3[secure] ; python_version < "3"
Requires-Dist: dataclasses ; python_version < "3.7"
Provides-Extra: yaml
Requires-Dist: PyYAML (>=3.10) ; extra == 'yaml'
